{
  "session_id": "session_20250628_154636",
  "start_time": "2025-06-28T15:46:36.199476",
  "timestamp": "20250628_154636",
  "log_files": {
    "main": "logs/session_20250628_154636_main.log",
    "errors": "logs/session_20250628_154636_errors.log",
    "debug": "logs/session_20250628_154636_debug.log",
    "automation": "logs/session_20250628_154636_automation.log",
    "api": "logs/session_20250628_154636_api.log",
    "security": "logs/session_20250628_154636_security.log"
  },
  "categories": {
    "main": "Main application logs",
    "errors": "Error and exception logs",
    "debug": "Debug and development logs",
    "automation": "Blog automation process logs",
    "api": "API requests and responses",
    "security": "Security-related events"
  },
  "status": "completed",
  "end_time": "2025-06-28T15:47:44.175467",
  "duration_seconds": 67.975991,
  "file_sizes": {
    "main": 1388,
    "errors": 0,
    "debug": 0,
    "automation": 0,
    "api": 0,
    "security": 0
  }
}